print_fn/__init__.py
print_fn/example.py
print_fn-0.1.dist-info/METADATA
print_fn-0.1.dist-info/WHEEL
print_fn-0.1.dist-info/top_level.txt
print_fn-0.1.dist-info/RECORD
