Metadata-Version: 2.4
Name: print_fn
Version: 0.1
Summary: Simple print function module
Author: savithri
Author-email: savithri2005muthuvel@gmail.com
Dynamic: author
Dynamic: author-email
Dynamic: summary
